aliendev_logger/__init__.py
aliendev_logger/main.py
aliendev_logger-0.1.0.dist-info/METADATA
aliendev_logger-0.1.0.dist-info/WHEEL
aliendev_logger-0.1.0.dist-info/RECORD
