Metadata-Version: 2.1
Name: aliendev-logger
Version: 0.1.0
Summary: 
Author: Nasri Adzlani
Author-email: nasriadzlani@live.com
Requires-Python: >=3.10,<4.0
Classifier: Programming Language :: Python :: 3
Classifier: Programming Language :: Python :: 3.10
Classifier: Programming Language :: Python :: 3.11
Requires-Dist: loguru (>=0.7.0,<0.8.0)
